[{"date":"2024-05-04","started":true,"venue_id":null,"innings":7,"earned_runs":0,"runs":0,"strikeouts":8,"walks":0,"hits":3,"home_runs":0,"pitches":85,"batters_faced":23},{"date":"2024-05-11","started":true,"venue_id":null,"innings":4.2,"earned_runs":4,"runs":4,"strikeouts":3,"walks":0,"hits":6,"home_runs":1,"pitches":89,"batters_faced":21},{"date":"2024-05-17","started":true,"venue_id":null,"innings":6,"earned_runs":2,"runs":2,"strikeouts":4,"walks":0,"hits":6,"home_runs":1,"pitches":95,"batters_faced":24},{"date":"2024-05-22","started":true,"venue_id":null,"innings":3,"earned_runs":0,"runs":0,"strikeouts":1,"walks":2,"hits":1,"home_runs":0,"pitches":51,"batters_faced":12}]