[{"date":"2025-03-31","started":true,"venue_id":null,"innings":4,"earned_runs":4,"runs":4,"strikeouts":3,"walks":1,"hits":6,"home_runs":1,"pitches":64,"batters_faced":19},{"date":"2025-04-05","started":true,"venue_id":null,"innings":5,"earned_runs":7,"runs":7,"strikeouts":2,"walks":1,"hits":8,"home_runs":4,"pitches":76,"batters_faced":23},{"date":"2025-04-10","started":false,"venue_id":null,"innings":0.1,"earned_runs":0,"runs":0,"strikeouts":1,"walks":0,"hits":1,"home_runs":0,"pitches":15,"batters_faced":2},{"date":"2025-04-14","started":false,"venue_id":null,"innings":5,"earned_runs":1,"runs":1,"strikeouts":7,"walks":0,"hits":3,"home_runs":1,"pitches":68,"batters_faced":18},{"date":"2025-05-03","started":false,"venue_id":null,"innings":1,"earned_runs":0,"runs":0,"strikeouts":2,"walks":1,"hits":0,"home_runs":0,"pitches":20,"batters_faced":4},{"date":"2025-05-07","started":false,"venue_id":null,"innings":3.1,"earned_runs":6,"runs":6,"strikeouts":2,"walks":4,"hits":5,"home_runs":1,"pitches":74,"batters_faced":18},{"date":"2025-08-04","started":false,"venue_id":null,"innings":1,"earned_runs":2,"runs":2,"strikeouts":1,"walks":0,"hits":3,"home_runs":2,"pitches":18,"batters_faced":6}]