{"timestamp":"2023-07-24T11:55:40Z","previous_timestamp":"2023-07-24T11:50:40Z","next_timestamp":"2023-07-24T12:00:40Z","data":[{"id":"43429f03f224b4625300eefcc79165d0","sport_key":"baseball_mlb","sport_title":"MLB","commence_time":"2023-07-24T17:10:00Z","home_team":"Detroit Tigers","away_team":"San Francisco Giants","bookmakers":[{"key":"draftkings","title":"DraftKings","last_update":"2023-07-24T11:54:13Z","markets":[{"key":"totals","last_update":"2023-07-24T11:54:13Z","outcomes":[{"name":"Over","price":1.95,"point":8.5},{"name":"Under","price":1.87,"point":8.5}]}]},{"key":"pointsbetus","title":"PointsBet (US)","last_update":"2023-07-24T11:55:00Z","markets":[{"key":"totals","last_update":"2023-07-24T11:55:00Z","outcomes":[{"name":"Over","price":1.95,"point":8.5},{"name":"Under","price":1.87,"point":8.5}]}]},{"key":"fanduel","title":"FanDuel","last_update":"2023-07-24T11:54:37Z","markets":[{"key":"totals","last_update":"2023-07-24T11:54:37Z","outcomes":[{"name":"Over","price":1.96,"point":8.5},{"name":"Under","price":1.85,"point":8.5}]}]}]},{"id":"56551b92229bfa823d851372ac9e2cbc","sport_key":"baseball_mlb","sport_title":"MLB","commence_time":"2023-07-24T22:40:00Z","home_team":"Philadelphia Phillies","away_team":"Baltimore Orioles","bookmakers":[{"key":"draftkings","title":"DraftKings","last_update":"2023-07-24T11:54:13Z","markets":[{"key":"totals","last_update":"2023-07-24T11:54:13Z","outcomes":[{"name":"Over","price":1.95,"point":9.5},{"name":"Under","price":1.87,"point":9.5}]}]},{"key":"fanduel","title":"FanDuel","last_update":"2023-07-24T11:54:37Z","markets":[{"key":"totals","last_update":"2023-07-24T11:54:37Z","outcomes":[{"name":"Over","price":1.94,"point":9.5},{"name":"Under","price":1.88,"point":9.5}]}]},{"key":"pointsbetus","title":"PointsBet (US)","last_update":"2023-07-24T11:55:00Z","markets":[{"key":"totals","last_update":"2023-07-24T11:55:00Z","outcomes":[{"name":"Over","price":1.91,"point":9.5},{"name":"Under","price":1.91,"point":9.5}]}]},{"key":"betmgm","title":"BetMGM","last_update":"2023-07-24T11:55:12Z","markets":[{"key":"totals","last_update":"2023-07-24T11:55:12Z","outcomes":[{"name":"Over","price":2,"point":9.5},{"name":"Under","price":1.83,"point":9.5}]}]}]},{"id":"39e223838940bca436f3601230153840","sport_key":"baseball_mlb","sport_title":"MLB","commence_time":"2023-07-24T23:05:00Z","home_team":"Washington Nationals","away_team":"Colorado Rockies","bookmakers":[{"key":"draftkings","title":"DraftKings","last_update":"2023-07-24T11:54:13Z","markets":[{"key":"totals","last_update":"2023-07-24T11:54:13Z","outcomes":[{"name":"Over","price":1.87,"point":9},{"name":"Under","price":1.95,"point":9}]}]},{"key":"pointsbetus","title":"PointsBet (US)","last_update":"2023-07-24T11:55:00Z","markets":[{"key":"totals","last_update":"2023-07-24T11:55:00Z","outcomes":[{"name":"Over","price":1.87,"point":9},{"name":"Under","price":1.95,"point":9}]}]},{"key":"fanduel","title":"FanDuel","last_update":"2023-07-24T11:54:37Z","markets":[{"key":"totals","last_update":"2023-07-24T11:54:37Z","outcomes":[{"name":"Over","price":1.85,"point":9},{"name":"Under","price":1.96,"point":9}]}]}]},{"id":"db02c98f7928c39aed6149b56379de1e","sport_key":"baseball_mlb","sport_title":"MLB","commence_time":"2023-07-24T23:10:00Z","home_team":"Cleveland Guardians","away_team":"Kansas City Royals","bookmakers":[{"key":"draftkings","title":"DraftKings","last_update":"2023-07-24T11:54:13Z","markets":[{"key":"totals","last_update":"2023-07-24T11:54:13Z","outcomes":[{"name":"Over","price":1.87,"point":8.5},{"name":"Under","price":1.95,"point":8.5}]}]},{"key":"fanduel","title":"FanDuel","last_update":"2023-07-24T11:54:37Z","markets":[{"key":"totals","last_update":"2023-07-24T11:54:37Z","outcomes":[{"name":"Over","price":1.87,"point":8.5},{"name":"Under","price":1.95,"point":8.5}]}]},{"key":"pointsbetus","title":"PointsBet (US)","last_update":"2023-07-24T11:55:00Z","markets":[{"key":"totals","last_update":"2023-07-24T11:55:00Z","outcomes":[{"name":"Over","price":1.87,"point":8.5},{"name":"Under","price":1.95,"point":8.5}]}]},{"key":"betmgm","title":"BetMGM","last_update":"2023-07-24T11:55:12Z","markets":[{"key":"totals","last_update":"2023-07-24T11:55:12Z","outcomes":[{"name":"Over","price":1.91,"point":8.5},{"name":"Under","price":1.91,"point":8.5}]}]}]},{"id":"c41252e2225e20647da884ba90a5aecc","sport_key":"baseball_mlb","sport_title":"MLB","commence_time":"2023-07-24T23:40:00Z","home_team":"Minnesota Twins","away_team":"Seattle Mariners","bookmakers":[{"key":"draftkings","title":"DraftKings","last_update":"2023-07-24T11:54:13Z","markets":[{"key":"totals","last_update":"2023-07-24T11:54:13Z","outcomes":[{"name":"Over","price":1.95,"point":8.5},{"name":"Under","price":1.87,"point":8.5}]}]},{"key":"fanduel","title":"FanDuel","last_update":"2023-07-24T11:54:37Z","markets":[{"key":"totals","last_update":"2023-07-24T11:54:37Z","outcomes":[{"name":"Over","price":1.87,"point":8},{"name":"Under","price":1.95,"point":8}]}]},{"key":"betmgm","title":"BetMGM","last_update":"2023-07-24T11:55:12Z","markets":[{"key":"totals","last_update":"2023-07-24T11:55:12Z","outcomes":[{"name":"Over","price":1.87,"point":8},{"name":"Under","price":1.95,"point":8}]}]},{"key":"pointsbetus","title":"PointsBet (US)","last_update":"2023-07-24T11:55:00Z","markets":[{"key":"totals","last_update":"2023-07-24T11:55:00Z","outcomes":[{"name":"Over","price":1.91,"point":8.5},{"name":"Under","price":1.91,"point":8.5}]}]}]},{"id":"5bf442cc3eb9a4d7c0c1ef92c11b33ce","sport_key":"baseball_mlb","sport_title":"MLB","commence_time":"2023-07-25T00:10:00Z","home_team":"Milwaukee Brewers","away_team":"Cincinnati Reds","bookmakers":[{"key":"draftkings","title":"DraftKings","last_update":"2023-07-24T11:54:13Z","markets":[{"key":"totals","last_update":"2023-07-24T11:54:13Z","outcomes":[{"name":"Over","price":1.91,"point":9},{"name":"Under","price":1.91,"point":9}]}]},{"key":"fanduel","title":"FanDuel","last_update":"2023-07-24T11:54:37Z","markets":[{"key":"totals","last_update":"2023-07-24T11:54:37Z","outcomes":[{"name":"Over","price":1.83,"point":9},{"name":"Under","price":1.98,"point":9}]}]},{"key":"betmgm","title":"BetMGM","last_update":"2023-07-24T11:55:12Z","markets":[{"key":"totals","last_update":"2023-07-24T11:55:12Z","outcomes":[{"name":"Over","price":1.87,"point":9},{"name":"Under","price":1.95,"point":9}]}]},{"key":"pointsbetus","title":"PointsBet (US)","last_update":"2023-07-24T11:55:00Z","markets":[{"key":"totals","last_update":"2023-07-24T11:55:00Z","outcomes":[{"name":"Over","price":1.91,"point":9},{"name":"Under","price":1.91,"point":9}]}]}]},{"id":"74ccfb375dd7632f12420ac5275de202","sport_key":"baseball_mlb","sport_title":"MLB","commence_time":"2023-07-25T00:10:00Z","home_team":"Houston Astros","away_team":"Texas Rangers","bookmakers":[{"key":"draftkings","title":"DraftKings","last_update":"2023-07-24T11:54:13Z","markets":[{"key":"totals","last_update":"2023-07-24T11:54:13Z","outcomes":[{"name":"Over","price":2,"point":9},{"name":"Under","price":1.83,"point":9}]}]},{"key":"fanduel","title":"FanDuel","last_update":"2023-07-24T11:54:37Z","markets":[{"key":"totals","last_update":"2023-07-24T11:54:37Z","outcomes":[{"name":"Over","price":1.85,"point":8.5},{"name":"Under","price":1.96,"point":8.5}]}]},{"key":"betmgm","title":"BetMGM","last_update":"2023-07-24T11:55:12Z","markets":[{"key":"totals","last_update":"2023-07-24T11:55:12Z","outcomes":[{"name":"Over","price":1.95,"point":9},{"name":"Under","price":1.87,"point":9}]}]},{"key":"pointsbetus","title":"PointsBet (US)","last_update":"2023-07-24T11:55:00Z","markets":[{"key":"totals","last_update":"2023-07-24T11:55:00Z","outcomes":[{"name":"Over","price":1.95,"point":9},{"name":"Under","price":1.87,"point":9}]}]}]},{"id":"2a39c07a4698e32b382120e7cf20d099","sport_key":"baseball_mlb","sport_title":"MLB","commence_time":"2023-07-25T01:40:00Z","home_team":"San Diego Padres","away_team":"Pittsburgh Pirates","bookmakers":[{"key":"draftkings","title":"DraftKings","last_update":"2023-07-24T11:54:13Z","markets":[{"key":"totals","last_update":"2023-07-24T11:54:13Z","outcomes":[{"name":"Over","price":1.91,"point":8.5},{"name":"Under","price":1.91,"point":8.5}]}]},{"key":"fanduel","title":"FanDuel","last_update":"2023-07-24T11:54:37Z","markets":[{"key":"totals","last_update":"2023-07-24T11:54:37Z","outcomes":[{"name":"Over","price":1.94,"point":8.5},{"name":"Under","price":1.88,"point":8.5}]}]},{"key":"betmgm","title":"BetMGM","last_update":"2023-07-24T11:55:12Z","markets":[{"key":"totals","last_update":"2023-07-24T11:55:12Z","outcomes":[{"name":"Over","price":1.95,"point":8.5},{"name":"Under","price":1.87,"point":8.5}]}]},{"key":"pointsbetus","title":"PointsBet (US)","last_update":"2023-07-24T11:55:00Z","markets":[{"key":"totals","last_update":"2023-07-24T11:55:00Z","outcomes":[{"name":"Over","price":1.95,"point":8.5},{"name":"Under","price":1.87,"point":8.5}]}]}]},{"id":"d0fa9f0da2b3630283997463c0755c85","sport_key":"baseball_mlb","sport_title":"MLB","commence_time":"2023-07-25T02:10:00Z","home_team":"Los Angeles Dodgers","away_team":"Toronto Blue Jays","bookmakers":[{"key":"draftkings","title":"DraftKings","last_update":"2023-07-24T11:54:13Z","markets":[{"key":"totals","last_update":"2023-07-24T11:54:13Z","outcomes":[{"name":"Over","price":1.95,"point":9.5},{"name":"Under","price":1.87,"point":9.5}]}]},{"key":"fanduel","title":"FanDuel","last_update":"2023-07-24T11:54:37Z","markets":[{"key":"totals","last_update":"2023-07-24T11:54:37Z","outcomes":[{"name":"Over","price":1.96,"point":9.5},{"name":"Under","price":1.85,"point":9.5}]}]},{"key":"betmgm","title":"BetMGM","last_update":"2023-07-24T11:55:12Z","markets":[{"key":"totals","last_update":"2023-07-24T11:55:12Z","outcomes":[{"name":"Over","price":1.83,"point":9},{"name":"Under","price":2,"point":9}]}]},{"key":"pointsbetus","title":"PointsBet (US)","last_update":"2023-07-24T11:55:00Z","markets":[{"key":"totals","last_update":"2023-07-24T11:55:00Z","outcomes":[{"name":"Over","price":1.95,"point":9.5},{"name":"Under","price":1.87,"point":9.5}]}]}]},{"id":"407dec919e4289f64a19f2c055664145","sport_key":"baseball_mlb","sport_title":"MLB","commence_time":"2023-07-25T22:40:00Z","home_team":"Philadelphia Phillies","away_team":"Baltimore Orioles","bookmakers":[{"key":"draftkings","title":"DraftKings","last_update":"2023-07-24T11:54:13Z","markets":[{"key":"totals","last_update":"2023-07-24T11:54:13Z","outcomes":[{"name":"Over","price":2,"point":9},{"name":"Under","price":1.83,"point":9}]}]}]},{"id":"a21db19a068b9de7b63cd1d45c542cb9","sport_key":"baseball_mlb","sport_title":"MLB","commence_time":"2023-07-25T22:40:00Z","home_team":"Detroit Tigers","away_team":"Los Angeles Angels","bookmakers":[{"key":"draftkings","title":"DraftKings","last_update":"2023-07-24T11:54:13Z","markets":[{"key":"totals","last_update":"2023-07-24T11:54:13Z","outcomes":[{"name":"Over","price":1.87,"point":8},{"name":"Under","price":1.95,"point":8}]}]}]},{"id":"e4a0297bc8f1295baa19c2dd74361cb1","sport_key":"baseball_mlb","sport_title":"MLB","commence_time":"2023-07-25T22:40:00Z","home_team":"Tampa Bay Rays","away_team":"Miami Marlins","bookmakers":[{"key":"draftkings","title":"DraftKings","last_update":"2023-07-24T11:54:13Z","markets":[{"key":"totals","last_update":"2023-07-24T11:54:13Z","outcomes":[{"name":"Over","price":1.8,"point":6.5},{"name":"Under","price":2.05,"point":6.5}]}]}]},{"id":"16de84a36b428daadd571af4fb2d26ea","sport_key":"baseball_mlb","sport_title":"MLB","commence_time":"2023-07-25T23:05:00Z","home_team":"New York Yankees","away_team":"New York Mets","bookmakers":[{"key":"draftkings","title":"DraftKings","last_update":"2023-07-24T11:54:13Z","markets":[{"key":"totals","last_update":"2023-07-24T11:54:13Z","outcomes":[{"name":"Over","price":1.95,"point":8},{"name":"Under","price":1.87,"point":8}]}]}]},{"id":"6f550b6ecf8ceafb70986a132f1e517d","sport_key":"baseball_mlb","sport_title":"MLB","commence_time":"2023-07-25T23:10:00Z","home_team":"Cleveland Guardians","away_team":"Kansas City Royals","bookmakers":[{"key":"draftkings","title":"DraftKings","last_update":"2023-07-24T11:54:13Z","markets":[{"key":"totals","last_update":"2023-07-24T11:54:13Z","outcomes":[{"name":"Over","price":1.87,"point":8.5},{"name":"Under","price":1.95,"point":8.5}]}]}]},{"id":"28e1efd576108ebf9acadf8d548c6f7b","sport_key":"baseball_mlb","sport_title":"MLB","commence_time":"2023-07-25T23:40:00Z","home_team":"Minnesota Twins","away_team":"Seattle Mariners","bookmakers":[{"key":"draftkings","title":"DraftKings","last_update":"2023-07-24T11:54:13Z","markets":[{"key":"totals","last_update":"2023-07-24T11:54:13Z","outcomes":[{"name":"Over","price":1.95,"point":7.5},{"name":"Under","price":1.87,"point":7.5}]}]}]},{"id":"c9487512ccf3f2018d4dc839f65f7698","sport_key":"baseball_mlb","sport_title":"MLB","commence_time":"2023-07-26T00:10:00Z","home_team":"Chicago White Sox","away_team":"Chicago Cubs","bookmakers":[{"key":"draftkings","title":"DraftKings","last_update":"2023-07-24T11:54:13Z","markets":[{"key":"totals","last_update":"2023-07-24T11:54:13Z","outcomes":[{"name":"Over","price":1.87,"point":8.5},{"name":"Under","price":1.95,"point":8.5}]}]}]},{"id":"2c527ead41fb64064fba8e7b0e926157","sport_key":"baseball_mlb","sport_title":"MLB","commence_time":"2023-07-26T00:10:00Z","home_team":"Milwaukee Brewers","away_team":"Cincinnati Reds","bookmakers":[{"key":"draftkings","title":"DraftKings","last_update":"2023-07-24T11:54:13Z","markets":[{"key":"totals","last_update":"2023-07-24T11:54:13Z","outcomes":[{"name":"Over","price":1.91,"point":8},{"name":"Under","price":1.91,"point":8}]}]}]},{"id":"f399477d2b7f5510b82785c02b2fcad4","sport_key":"baseball_mlb","sport_title":"MLB","commence_time":"2023-07-26T02:10:00Z","home_team":"Los Angeles Dodgers","away_team":"Toronto Blue Jays","bookmakers":[{"key":"draftkings","title":"DraftKings","last_update":"2023-07-24T11:54:13Z","markets":[{"key":"totals","last_update":"2023-07-24T11:54:13Z","outcomes":[{"name":"Over","price":2,"point":9},{"name":"Under","price":1.83,"point":9}]}]}]}]}