{"timestamp":"2021-06-02T11:55:00Z","previous_timestamp":"2021-06-02T11:45:00Z","next_timestamp":"2021-06-02T12:05:00Z","data":[{"id":"abccf750eff3993af4e4fb705ad38b7c","sport_key":"baseball_mlb","sport_title":"MLB","commence_time":"2021-06-02T19:40:00Z","home_team":"Arizona Diamondbacks","away_team":"New York Mets","bookmakers":[{"key":"pointsbetus","title":"PointsBet (US)","last_update":"2021-06-02T11:48:27Z","markets":[{"key":"totals","last_update":"2021-06-02T11:48:27Z","outcomes":[{"name":"Over","price":1.83,"point":8},{"name":"Under","price":2,"point":8}]}]},{"key":"betmgm","title":"BetMGM","last_update":"2021-06-02T11:47:42Z","markets":[{"key":"totals","last_update":"2021-06-02T11:47:42Z","outcomes":[{"name":"Over","price":2,"point":8.5},{"name":"Under","price":1.83,"point":8.5}]}]}]},{"id":"7eacf9f1773012f9baf52c3cd8f3d46b","sport_key":"baseball_mlb","sport_title":"MLB","commence_time":"2021-06-02T17:10:00Z","home_team":"Cleveland Indians","away_team":"Chicago White Sox","bookmakers":[]},{"id":"87ad6ccbdfd101497ca0c45f70ea455b","sport_key":"baseball_mlb","sport_title":"MLB","commence_time":"2021-06-02T23:05:00Z","home_team":"New York Yankees","away_team":"Tampa Bay Rays","bookmakers":[{"key":"pointsbetus","title":"PointsBet (US)","last_update":"2021-06-02T11:48:27Z","markets":[{"key":"totals","last_update":"2021-06-02T11:48:27Z","outcomes":[{"name":"Over","price":2,"point":8.5},{"name":"Under","price":1.83,"point":8.5}]}]},{"key":"betmgm","title":"BetMGM","last_update":"2021-06-02T11:47:42Z","markets":[{"key":"totals","last_update":"2021-06-02T11:47:42Z","outcomes":[{"name":"Over","price":1.87,"point":8},{"name":"Under","price":1.95,"point":8}]}]}]},{"id":"aeacab744f39017e98bb66d31704dd43","sport_key":"baseball_mlb","sport_title":"MLB","commence_time":"2021-06-02T23:07:00Z","home_team":"Toronto Blue Jays","away_team":"Miami Marlins","bookmakers":[{"key":"pointsbetus","title":"PointsBet (US)","last_update":"2021-06-02T11:48:27Z","markets":[{"key":"totals","last_update":"2021-06-02T11:48:27Z","outcomes":[{"name":"Over","price":1.87,"point":8},{"name":"Under","price":1.95,"point":8}]}]},{"key":"betmgm","title":"BetMGM","last_update":"2021-06-02T11:47:42Z","markets":[{"key":"totals","last_update":"2021-06-02T11:47:42Z","outcomes":[{"name":"Over","price":1.87,"point":8},{"name":"Under","price":1.95,"point":8}]}]}]},{"id":"12c97b15cc3080ad1311f88199d1ac1d","sport_key":"baseball_mlb","sport_title":"MLB","commence_time":"2021-06-03T00:10:00Z","home_team":"Houston Astros","away_team":"Boston Red Sox","bookmakers":[{"key":"pointsbetus","title":"PointsBet (US)","last_update":"2021-06-02T11:48:27Z","markets":[{"key":"totals","last_update":"2021-06-02T11:48:27Z","outcomes":[{"name":"Over","price":1.91,"point":8.5},{"name":"Under","price":1.91,"point":8.5}]}]},{"key":"betmgm","title":"BetMGM","last_update":"2021-06-02T11:47:42Z","markets":[{"key":"totals","last_update":"2021-06-02T11:47:42Z","outcomes":[{"name":"Over","price":1.91,"point":8.5},{"name":"Under","price":1.91,"point":8.5}]}]}]},{"id":"49882407ec0a9001bc2d676a607fa44c","sport_key":"baseball_mlb","sport_title":"MLB","commence_time":"2021-06-03T00:40:00Z","home_team":"Colorado Rockies","away_team":"Texas Rangers","bookmakers":[{"key":"pointsbetus","title":"PointsBet (US)","last_update":"2021-06-02T11:48:27Z","markets":[{"key":"totals","last_update":"2021-06-02T11:48:27Z","outcomes":[{"name":"Over","price":1.95,"point":11},{"name":"Under","price":1.87,"point":11}]}]},{"key":"betmgm","title":"BetMGM","last_update":"2021-06-02T11:47:42Z","markets":[{"key":"totals","last_update":"2021-06-02T11:47:42Z","outcomes":[{"name":"Over","price":1.91,"point":11},{"name":"Under","price":1.91,"point":11}]}]}]},{"id":"2d6ea5992389814e8ac60b3031765a7e","sport_key":"baseball_mlb","sport_title":"MLB","commence_time":"2021-06-03T01:10:00Z","home_team":"Los Angeles Dodgers","away_team":"St. Louis Cardinals","bookmakers":[{"key":"pointsbetus","title":"PointsBet (US)","last_update":"2021-06-02T11:48:27Z","markets":[{"key":"totals","last_update":"2021-06-02T11:48:27Z","outcomes":[{"name":"Over","price":1.95,"point":8},{"name":"Under","price":1.87,"point":8}]}]},{"key":"betmgm","title":"BetMGM","last_update":"2021-06-02T11:47:42Z","markets":[{"key":"totals","last_update":"2021-06-02T11:47:42Z","outcomes":[{"name":"Over","price":1.87,"point":7.5},{"name":"Under","price":1.95,"point":7.5}]}]}]},{"id":"51bd33936b8607b228c0b6868b6d70ae","sport_key":"baseball_mlb","sport_title":"MLB","commence_time":"2021-06-03T02:10:00Z","home_team":"Seattle Mariners","away_team":"Oakland Athletics","bookmakers":[{"key":"pointsbetus","title":"PointsBet (US)","last_update":"2021-06-02T11:48:27Z","markets":[{"key":"totals","last_update":"2021-06-02T11:48:27Z","outcomes":[{"name":"Over","price":1.91,"point":8},{"name":"Under","price":1.91,"point":8}]}]},{"key":"betmgm","title":"BetMGM","last_update":"2021-06-02T11:47:42Z","markets":[{"key":"totals","last_update":"2021-06-02T11:47:42Z","outcomes":[{"name":"Over","price":1.87,"point":8},{"name":"Under","price":1.95,"point":8}]}]}]},{"id":"190a0087a53ab1a5692f9c56704043c8","sport_key":"baseball_mlb","sport_title":"MLB","commence_time":"2021-06-02T23:06:00Z","home_team":"Baltimore Orioles","away_team":"Minnesota Twins","bookmakers":[{"key":"betmgm","title":"BetMGM","last_update":"2021-06-02T11:47:42Z","markets":[{"key":"totals","last_update":"2021-06-02T11:47:42Z","outcomes":[{"name":"Over","price":1.91,"point":9.5},{"name":"Under","price":1.91,"point":9.5}]}]}]},{"id":"98a2b229bf56440ef821e0fb0807d6e6","sport_key":"baseball_mlb","sport_title":"MLB","commence_time":"2021-06-02T23:21:00Z","home_team":"Atlanta Braves","away_team":"Washington Nationals","bookmakers":[{"key":"betmgm","title":"BetMGM","last_update":"2021-06-02T11:47:42Z","markets":[{"key":"totals","last_update":"2021-06-02T11:47:42Z","outcomes":[{"name":"Over","price":1.87,"point":9.5},{"name":"Under","price":1.95,"point":9.5}]}]}]},{"id":"c052c5a48a264ec93802f46efd09c02f","sport_key":"baseball_mlb","sport_title":"MLB","commence_time":"2021-06-02T16:35:00Z","home_team":"Cincinnati Reds","away_team":"Philadelphia Phillies","bookmakers":[{"key":"pointsbetus","title":"PointsBet (US)","last_update":"2021-06-02T11:48:27Z","markets":[{"key":"totals","last_update":"2021-06-02T11:48:27Z","outcomes":[{"name":"Over","price":1.91,"point":8},{"name":"Under","price":1.91,"point":8}]}]},{"key":"betmgm","title":"BetMGM","last_update":"2021-06-02T11:47:42Z","markets":[{"key":"totals","last_update":"2021-06-02T11:47:42Z","outcomes":[{"name":"Over","price":1.95,"point":8},{"name":"Under","price":1.87,"point":8}]}]}]},{"id":"fd5db077eb9a018f978ac74ebfef71b2","sport_key":"baseball_mlb","sport_title":"MLB","commence_time":"2021-06-02T18:20:00Z","home_team":"Chicago Cubs","away_team":"San Diego Padres","bookmakers":[]}]}