{"timestamp":"2022-08-05T11:55:00Z","previous_timestamp":"2022-08-05T11:45:00Z","next_timestamp":"2022-08-05T12:05:00Z","data":[{"id":"44480d81744e504b927e37966bb95b21","sport_key":"baseball_mlb","sport_title":"MLB","commence_time":"2022-08-05T23:06:00Z","home_team":"Philadelphia Phillies","away_team":"Washington Nationals","bookmakers":[{"key":"draftkings","title":"DraftKings","last_update":"2022-08-05T11:47:20Z","markets":[{"key":"totals","last_update":"2022-08-05T11:47:20Z","outcomes":[{"name":"Over","price":1.83,"point":8.5},{"name":"Under","price":2,"point":8.5}]}]},{"key":"fanduel","title":"FanDuel","last_update":"2022-08-05T11:47:22Z","markets":[{"key":"totals","last_update":"2022-08-05T11:47:22Z","outcomes":[{"name":"Over","price":1.96,"point":9},{"name":"Under","price":1.85,"point":9}]}]},{"key":"pointsbetus","title":"PointsBet (US)","last_update":"2022-08-05T11:47:21Z","markets":[{"key":"totals","last_update":"2022-08-05T11:47:21Z","outcomes":[{"name":"Over","price":1.8,"point":8.5},{"name":"Under","price":2.05,"point":8.5}]}]},{"key":"betmgm","title":"BetMGM","last_update":"2022-08-05T11:48:01Z","markets":[{"key":"totals","last_update":"2022-08-05T11:48:01Z","outcomes":[{"name":"Over","price":1.83,"point":8.5},{"name":"Under","price":2,"point":8.5}]}]}]},{"id":"c6c620193b836a7a6e207c8f2a5c8180","sport_key":"baseball_mlb","sport_title":"MLB","commence_time":"2022-08-05T23:11:00Z","home_team":"New York Mets","away_team":"Atlanta Braves","bookmakers":[{"key":"draftkings","title":"DraftKings","last_update":"2022-08-05T11:47:20Z","markets":[{"key":"totals","last_update":"2022-08-05T11:47:20Z","outcomes":[{"name":"Over","price":1.91,"point":8.5},{"name":"Under","price":1.91,"point":8.5}]}]},{"key":"fanduel","title":"FanDuel","last_update":"2022-08-05T11:47:22Z","markets":[{"key":"totals","last_update":"2022-08-05T11:47:22Z","outcomes":[{"name":"Over","price":1.89,"point":8.5},{"name":"Under","price":1.93,"point":8.5}]}]},{"key":"pointsbetus","title":"PointsBet (US)","last_update":"2022-08-05T11:47:21Z","markets":[{"key":"totals","last_update":"2022-08-05T11:47:21Z","outcomes":[{"name":"Over","price":1.91,"point":8.5},{"name":"Under","price":1.91,"point":8.5}]}]},{"key":"betmgm","title":"BetMGM","last_update":"2022-08-05T11:48:01Z","markets":[{"key":"totals","last_update":"2022-08-05T11:48:01Z","outcomes":[{"name":"Over","price":1.91,"point":8.5},{"name":"Under","price":1.91,"point":8.5}]}]}]},{"id":"ac57f26c4a06adcb6150c5c82cd62831","sport_key":"baseball_mlb","sport_title":"MLB","commence_time":"2022-08-06T00:06:00Z","home_team":"Texas Rangers","away_team":"Chicago White Sox","bookmakers":[{"key":"draftkings","title":"DraftKings","last_update":"2022-08-05T11:47:20Z","markets":[{"key":"totals","last_update":"2022-08-05T11:47:20Z","outcomes":[{"name":"Over","price":1.95,"point":8},{"name":"Under","price":1.87,"point":8}]}]},{"key":"pointsbetus","title":"PointsBet (US)","last_update":"2022-08-05T11:47:21Z","markets":[{"key":"totals","last_update":"2022-08-05T11:47:21Z","outcomes":[{"name":"Over","price":2,"point":8},{"name":"Under","price":1.83,"point":8}]}]},{"key":"fanduel","title":"FanDuel","last_update":"2022-08-05T11:47:22Z","markets":[{"key":"totals","last_update":"2022-08-05T11:47:22Z","outcomes":[{"name":"Over","price":1.95,"point":8},{"name":"Under","price":1.87,"point":8}]}]},{"key":"betmgm","title":"BetMGM","last_update":"2022-08-05T11:48:01Z","markets":[{"key":"totals","last_update":"2022-08-05T11:48:01Z","outcomes":[{"name":"Over","price":1.95,"point":8},{"name":"Under","price":1.87,"point":8}]}]}]},{"id":"83a0f58610a834c950ac143624589d8e","sport_key":"baseball_mlb","sport_title":"MLB","commence_time":"2022-08-06T02:11:00Z","home_team":"Los Angeles Dodgers","away_team":"San Diego Padres","bookmakers":[{"key":"fanduel","title":"FanDuel","last_update":"2022-08-05T11:47:22Z","markets":[{"key":"totals","last_update":"2022-08-05T11:47:22Z","outcomes":[{"name":"Over","price":1.85,"point":8.5},{"name":"Under","price":1.96,"point":8.5}]}]},{"key":"pointsbetus","title":"PointsBet (US)","last_update":"2022-08-05T11:47:21Z","markets":[{"key":"totals","last_update":"2022-08-05T11:47:21Z","outcomes":[{"name":"Over","price":1.87,"point":8.5},{"name":"Under","price":1.95,"point":8.5}]}]},{"key":"draftkings","title":"DraftKings","last_update":"2022-08-05T11:47:20Z","markets":[{"key":"totals","last_update":"2022-08-05T11:47:20Z","outcomes":[{"name":"Over","price":1.91,"point":8.5},{"name":"Under","price":1.91,"point":8.5}]}]},{"key":"betmgm","title":"BetMGM","last_update":"2022-08-05T11:48:01Z","markets":[{"key":"totals","last_update":"2022-08-05T11:48:01Z","outcomes":[{"name":"Over","price":1.87,"point":8.5},{"name":"Under","price":1.95,"point":8.5}]}]}]},{"id":"4e3054dd65b3d16f3bfc404a60d5ff8a","sport_key":"baseball_mlb","sport_title":"MLB","commence_time":"2022-08-06T02:11:00Z","home_team":"Seattle Mariners","away_team":"Los Angeles Angels","bookmakers":[{"key":"draftkings","title":"DraftKings","last_update":"2022-08-05T11:47:20Z","markets":[{"key":"totals","last_update":"2022-08-05T11:47:20Z","outcomes":[{"name":"Over","price":2,"point":7},{"name":"Under","price":1.83,"point":7}]}]},{"key":"fanduel","title":"FanDuel","last_update":"2022-08-05T11:47:22Z","markets":[{"key":"totals","last_update":"2022-08-05T11:47:22Z","outcomes":[{"name":"Over","price":1.98,"point":7},{"name":"Under","price":1.83,"point":7}]}]},{"key":"pointsbetus","title":"PointsBet (US)","last_update":"2022-08-05T11:47:21Z","markets":[{"key":"totals","last_update":"2022-08-05T11:47:21Z","outcomes":[{"name":"Over","price":2,"point":7},{"name":"Under","price":1.83,"point":7}]}]},{"key":"betmgm","title":"BetMGM","last_update":"2022-08-05T11:48:01Z","markets":[{"key":"totals","last_update":"2022-08-05T11:48:01Z","outcomes":[{"name":"Over","price":2,"point":7},{"name":"Under","price":1.83,"point":7}]}]}]},{"id":"ab135fef0eaf511bff94af3894d98f13","sport_key":"baseball_mlb","sport_title":"MLB","commence_time":"2022-08-06T01:41:00Z","home_team":"Arizona Diamondbacks","away_team":"Colorado Rockies","bookmakers":[{"key":"fanduel","title":"FanDuel","last_update":"2022-08-05T11:47:22Z","markets":[{"key":"totals","last_update":"2022-08-05T11:47:22Z","outcomes":[{"name":"Over","price":1.91,"point":8.5},{"name":"Under","price":1.91,"point":8.5}]}]},{"key":"draftkings","title":"DraftKings","last_update":"2022-08-05T11:47:20Z","markets":[{"key":"totals","last_update":"2022-08-05T11:47:20Z","outcomes":[{"name":"Over","price":1.91,"point":8.5},{"name":"Under","price":1.91,"point":8.5}]}]},{"key":"betmgm","title":"BetMGM","last_update":"2022-08-05T11:48:01Z","markets":[{"key":"totals","last_update":"2022-08-05T11:48:01Z","outcomes":[{"name":"Over","price":1.91,"point":8.5},{"name":"Under","price":1.91,"point":8.5}]}]},{"key":"pointsbetus","title":"PointsBet (US)","last_update":"2022-08-05T11:47:21Z","markets":[{"key":"totals","last_update":"2022-08-05T11:47:21Z","outcomes":[{"name":"Over","price":1.91,"point":8.5},{"name":"Under","price":1.91,"point":8.5}]}]}]},{"id":"b814e801b18a3926129f8c14213ca68f","sport_key":"baseball_mlb","sport_title":"MLB","commence_time":"2022-08-06T00:16:00Z","home_team":"St. Louis Cardinals","away_team":"New York Yankees","bookmakers":[{"key":"fanduel","title":"FanDuel","last_update":"2022-08-05T11:47:22Z","markets":[{"key":"totals","last_update":"2022-08-05T11:47:22Z","outcomes":[{"name":"Over","price":1.96,"point":8.5},{"name":"Under","price":1.85,"point":8.5}]}]},{"key":"pointsbetus","title":"PointsBet (US)","last_update":"2022-08-05T11:47:21Z","markets":[{"key":"totals","last_update":"2022-08-05T11:47:21Z","outcomes":[{"name":"Over","price":1.95,"point":8.5},{"name":"Under","price":1.87,"point":8.5}]}]},{"key":"draftkings","title":"DraftKings","last_update":"2022-08-05T11:47:20Z","markets":[{"key":"totals","last_update":"2022-08-05T11:47:20Z","outcomes":[{"name":"Over","price":1.95,"point":8.5},{"name":"Under","price":1.87,"point":8.5}]}]},{"key":"betmgm","title":"BetMGM","last_update":"2022-08-05T11:48:01Z","markets":[{"key":"totals","last_update":"2022-08-05T11:48:01Z","outcomes":[{"name":"Over","price":1.95,"point":8.5},{"name":"Under","price":1.87,"point":8.5}]}]}]},{"id":"9ac1a6784a6e81c2da075d343741ea68","sport_key":"baseball_mlb","sport_title":"MLB","commence_time":"2022-08-06T00:11:00Z","home_team":"Milwaukee Brewers","away_team":"Cincinnati Reds","bookmakers":[{"key":"draftkings","title":"DraftKings","last_update":"2022-08-05T11:47:20Z","markets":[{"key":"totals","last_update":"2022-08-05T11:47:20Z","outcomes":[{"name":"Over","price":1.95,"point":9},{"name":"Under","price":1.87,"point":9}]}]},{"key":"fanduel","title":"FanDuel","last_update":"2022-08-05T11:47:22Z","markets":[{"key":"totals","last_update":"2022-08-05T11:47:22Z","outcomes":[{"name":"Over","price":1.95,"point":9},{"name":"Under","price":1.87,"point":9}]}]},{"key":"pointsbetus","title":"PointsBet (US)","last_update":"2022-08-05T11:47:21Z","markets":[{"key":"totals","last_update":"2022-08-05T11:47:21Z","outcomes":[{"name":"Over","price":1.91,"point":9},{"name":"Under","price":1.91,"point":9}]}]},{"key":"betmgm","title":"BetMGM","last_update":"2022-08-05T11:48:01Z","markets":[{"key":"totals","last_update":"2022-08-05T11:48:01Z","outcomes":[{"name":"Over","price":1.91,"point":9},{"name":"Under","price":1.91,"point":9}]}]}]},{"id":"39680c708ccebdabad4af6dfb82120dc","sport_key":"baseball_mlb","sport_title":"MLB","commence_time":"2022-08-05T23:06:00Z","home_team":"Baltimore Orioles","away_team":"Pittsburgh Pirates","bookmakers":[{"key":"fanduel","title":"FanDuel","last_update":"2022-08-05T11:47:22Z","markets":[{"key":"totals","last_update":"2022-08-05T11:47:22Z","outcomes":[{"name":"Over","price":1.91,"point":8.5},{"name":"Under","price":1.91,"point":8.5}]}]},{"key":"draftkings","title":"DraftKings","last_update":"2022-08-05T11:47:20Z","markets":[{"key":"totals","last_update":"2022-08-05T11:47:20Z","outcomes":[{"name":"Over","price":1.87,"point":8.5},{"name":"Under","price":1.95,"point":8.5}]}]},{"key":"betmgm","title":"BetMGM","last_update":"2022-08-05T11:48:01Z","markets":[{"key":"totals","last_update":"2022-08-05T11:48:01Z","outcomes":[{"name":"Over","price":1.87,"point":8.5},{"name":"Under","price":1.95,"point":8.5}]}]},{"key":"pointsbetus","title":"PointsBet (US)","last_update":"2022-08-05T11:47:21Z","markets":[{"key":"totals","last_update":"2022-08-05T11:47:21Z","outcomes":[{"name":"Over","price":1.87,"point":8.5},{"name":"Under","price":1.95,"point":8.5}]}]}]},{"id":"424214389375c4d36b41d7ff5eebb07e","sport_key":"baseball_mlb","sport_title":"MLB","commence_time":"2022-08-05T23:11:00Z","home_team":"Detroit Tigers","away_team":"Tampa Bay Rays","bookmakers":[{"key":"pointsbetus","title":"PointsBet (US)","last_update":"2022-08-05T11:47:21Z","markets":[{"key":"totals","last_update":"2022-08-05T11:47:21Z","outcomes":[{"name":"Over","price":1.91,"point":8.5},{"name":"Under","price":1.91,"point":8.5}]}]},{"key":"fanduel","title":"FanDuel","last_update":"2022-08-05T11:47:22Z","markets":[{"key":"totals","last_update":"2022-08-05T11:47:22Z","outcomes":[{"name":"Over","price":1.91,"point":8.5},{"name":"Under","price":1.91,"point":8.5}]}]},{"key":"draftkings","title":"DraftKings","last_update":"2022-08-05T11:47:20Z","markets":[{"key":"totals","last_update":"2022-08-05T11:47:20Z","outcomes":[{"name":"Over","price":1.91,"point":8.5},{"name":"Under","price":1.91,"point":8.5}]}]},{"key":"betmgm","title":"BetMGM","last_update":"2022-08-05T11:48:01Z","markets":[{"key":"totals","last_update":"2022-08-05T11:48:01Z","outcomes":[{"name":"Over","price":1.91,"point":8.5},{"name":"Under","price":1.91,"point":8.5}]}]}]},{"id":"c22b73172f98224770b37b6c90de8979","sport_key":"baseball_mlb","sport_title":"MLB","commence_time":"2022-08-06T00:11:00Z","home_team":"Minnesota Twins","away_team":"Toronto Blue Jays","bookmakers":[{"key":"pointsbetus","title":"PointsBet (US)","last_update":"2022-08-05T11:47:21Z","markets":[{"key":"totals","last_update":"2022-08-05T11:47:21Z","outcomes":[{"name":"Over","price":2,"point":9},{"name":"Under","price":1.83,"point":9}]}]},{"key":"fanduel","title":"FanDuel","last_update":"2022-08-05T11:47:22Z","markets":[{"key":"totals","last_update":"2022-08-05T11:47:22Z","outcomes":[{"name":"Over","price":1.83,"point":8.5},{"name":"Under","price":1.98,"point":8.5}]}]},{"key":"betmgm","title":"BetMGM","last_update":"2022-08-05T11:48:01Z","markets":[{"key":"totals","last_update":"2022-08-05T11:48:01Z","outcomes":[{"name":"Over","price":1.83,"point":8.5},{"name":"Under","price":2,"point":8.5}]}]},{"key":"draftkings","title":"DraftKings","last_update":"2022-08-05T11:47:20Z","markets":[{"key":"totals","last_update":"2022-08-05T11:47:20Z","outcomes":[{"name":"Over","price":2,"point":9},{"name":"Under","price":1.83,"point":9}]}]}]},{"id":"56196178c2a966e0a020469a6e1fe20a","sport_key":"baseball_mlb","sport_title":"MLB","commence_time":"2022-08-06T00:11:00Z","home_team":"Kansas City Royals","away_team":"Boston Red Sox","bookmakers":[{"key":"fanduel","title":"FanDuel","last_update":"2022-08-05T11:47:22Z","markets":[{"key":"totals","last_update":"2022-08-05T11:47:22Z","outcomes":[{"name":"Over","price":1.94,"point":9},{"name":"Under","price":1.88,"point":9}]}]},{"key":"pointsbetus","title":"PointsBet (US)","last_update":"2022-08-05T11:47:21Z","markets":[{"key":"totals","last_update":"2022-08-05T11:47:21Z","outcomes":[{"name":"Over","price":1.95,"point":9},{"name":"Under","price":1.87,"point":9}]}]},{"key":"draftkings","title":"DraftKings","last_update":"2022-08-05T11:47:20Z","markets":[{"key":"totals","last_update":"2022-08-05T11:47:20Z","outcomes":[{"name":"Over","price":2,"point":9},{"name":"Under","price":1.83,"point":9}]}]},{"key":"betmgm","title":"BetMGM","last_update":"2022-08-05T11:48:01Z","markets":[{"key":"totals","last_update":"2022-08-05T11:48:01Z","outcomes":[{"name":"Over","price":1.95,"point":9},{"name":"Under","price":1.87,"point":9}]}]}]},{"id":"f0e98421132a110ff6a394536bfde46c","sport_key":"baseball_mlb","sport_title":"MLB","commence_time":"2022-08-05T23:11:00Z","home_team":"Cleveland Guardians","away_team":"Houston Astros","bookmakers":[{"key":"draftkings","title":"DraftKings","last_update":"2022-08-05T11:47:20Z","markets":[{"key":"totals","last_update":"2022-08-05T11:47:20Z","outcomes":[{"name":"Over","price":1.87,"point":8.5},{"name":"Under","price":1.95,"point":8.5}]}]},{"key":"fanduel","title":"FanDuel","last_update":"2022-08-05T11:47:22Z","markets":[{"key":"totals","last_update":"2022-08-05T11:47:22Z","outcomes":[{"name":"Over","price":1.83,"point":8.5},{"name":"Under","price":1.98,"point":8.5}]}]},{"key":"betmgm","title":"BetMGM","last_update":"2022-08-05T11:48:01Z","markets":[{"key":"totals","last_update":"2022-08-05T11:48:01Z","outcomes":[{"name":"Over","price":1.87,"point":8.5},{"name":"Under","price":1.95,"point":8.5}]}]},{"key":"pointsbetus","title":"PointsBet (US)","last_update":"2022-08-05T11:47:21Z","markets":[{"key":"totals","last_update":"2022-08-05T11:47:21Z","outcomes":[{"name":"Over","price":1.87,"point":8.5},{"name":"Under","price":1.95,"point":8.5}]}]}]}]}